where_was_i/__init__.py
where_was_i/cli.py
where_was_i/known_locations.py
where_was_i-0.2.3.data/data/LICENSE
where_was_i-0.2.3.dist-info/LICENSE
where_was_i-0.2.3.dist-info/METADATA
where_was_i-0.2.3.dist-info/WHEEL
where_was_i-0.2.3.dist-info/entry_points.txt
where_was_i-0.2.3.dist-info/top_level.txt
where_was_i-0.2.3.dist-info/RECORD
